biorxivist/__init__.py
biorxivist/webtools.py
biorxivist-0.2.1.dist-info/LICENSE
biorxivist-0.2.1.dist-info/METADATA
biorxivist-0.2.1.dist-info/WHEEL
biorxivist-0.2.1.dist-info/RECORD
