Metadata-Version: 2.1
Name: biorxivist
Version: 0.2.1
Summary: Tools to access prepublications from BioRxiv and integrate LLM tools.
License: MIT
Author: Ted Johnson
Requires-Python: >=3.10,<4.0
Classifier: License :: OSI Approved :: MIT License
Classifier: Programming Language :: Python :: 3
Classifier: Programming Language :: Python :: 3.10
Classifier: Programming Language :: Python :: 3.11
Classifier: Programming Language :: Python :: 3.12
Requires-Dist: beautifulsoup4 (>=4.12.2,<5.0.0)
Requires-Dist: ipython (>=8.17.2,<9.0.0)
Requires-Dist: jupyter (>=1.0.0,<2.0.0)
Requires-Dist: jupyterlab (>=4.0.8,<5.0.0)
Requires-Dist: langchain (>=0.0.330,<0.0.331)
Requires-Dist: neo4j (>=5.14.1,<6.0.0)
Requires-Dist: openai (==0.28.1)
Requires-Dist: pre-commit (>=3.5.0,<4.0.0)
Requires-Dist: python-dotenv (>=1.0.0,<2.0.0)
Requires-Dist: requests (>=2.31.0,<3.0.0)
Requires-Dist: tiktoken (>=0.5.1,<0.6.0)
Requires-Dist: unstructured (>=0.10.29,<0.11.0)
